skorovarka/__init__.py
skorovarka/main.py
skorovarka/parse_yaml.py
skorovarka/process.py
tests/__init__.py
tests/test_dir_processor.py
tests/test_patterns.py
skorovarka-1.0.0.dist-info/METADATA
skorovarka-1.0.0.dist-info/WHEEL
skorovarka-1.0.0.dist-info/entry_points.txt
skorovarka-1.0.0.dist-info/top_level.txt
skorovarka-1.0.0.dist-info/RECORD
