Metadata-Version: 2.1
Name: skorovarka
Version: 1.0.0
Summary: Speed up creation of repositories from templates
Home-page: https://github.com/kjczarne/skorovarka
Author: Krzysztof J. Czarnecki
Author-email: kcjzarne@gmail.com
License: MIT
Keywords: template,repository,deployment
Platform: UNKNOWN
Classifier: Programming Language :: Python :: 3
Classifier: License :: OSI Approved :: MIT License
Classifier: Operating System :: OS Independent
Requires-Python: >=3.7
Requires-Dist: mypy
Requires-Dist: pyyaml
Requires-Dist: pylint
Requires-Dist: termcolor
